<?xml version="1.0" encoding="UTF-8"?>
<!DOCTYPE hibernate-mapping PUBLIC
		"-//Hibernate/Hibernate Mapping DTD 3.0//EN"
		"http://hibernate.sourceforge.net/hibernate-mapping-3.0.dtd">
<hibernate-mapping>
	<class name="bean.Employer" table="EMPLOYER">
		
		<id name="ID" type="java.lang.Integer">
			<column name="ID" length="20" />
			<generator class="assigned"></generator>
		</id>
		
		<property name="EId" type="java.lang.Integer">
			<column name="EID" length="20"/>
		</property>
		<property name="Name" type="java.lang.String">
			<column name="NAME" length="20"/>
		</property>
		<property name="Sex" type="java.lang.String">
			<column name="SEX" length="20"/>
		</property>
		
		<property name="Location" type="java.lang.String">
			<column name="LOCATION" length="20"/>
		</property>
		<property name="Email" type="java.lang.String">
			<column name="EMAIL" length="20"/>
		</property>
		<property name="Department" type="java.lang.String">
			<column name="DEPART" length="20"/>
		</property>
		<property name="departmentNumber" type="java.lang.Integer">
			<column name="DEPARTNUMBER" length="20"/>
		</property>
		<property name="Telephone" type="java.lang.String">
			<column name="TELEPHONE" length="20"/>
		</property>
		
		<property name="Age" type="java.lang.Integer">
			<column name="AGE" length="20"/>
		</property>
		
		<property name="Birthday" type="java.lang.String">
			<column name="BIRTH" length="20"/>
		</property>
		<property name="Notes" type="java.lang.String">
			<column name="NOTES" length="100"/>
		</property>
		
		<property name="offerTime" type="java.lang.String">
			<column name="OFFERTIME" length="20"/>
		</property>
		
		<property name="status" type="java.lang.Integer">
			<column name="STATUS" length="20"/>
		</property>
		
		<property name="password" type="java.lang.String">
			<column name="PASSWORD" length="20"/>
		</property>
		
		<property name="IconUrl" type="java.lang.String">
			<column name="ICONURL" length="100"/>
		</property>
		
	
	</class>



</hibernate-mapping>